Workbook
Name aporte: Planilha1!$D$20:$D$20
Name patrimonio: Planilha1!$D$23:$D$23
Name qtd_anos: Planilha1!$D$21:$D$21
Name rendimento_carteira: Planilha1!$D$16:$D$16
Name salario: Planilha1!$D$15:$D$15
Name sugestao_investimento: Planilha1!$D$17:$D$17
Name taxa_mensal: Planilha1!$D$22:$D$22

Sheet Planilha1
B14: CONFIGURAÇÕES
B15: Salário | D15: 4200
B16: Rendimento em Carteira | D16: 0.009
B17: Sugestão de Investimento | D17: {=salario*30%} -> 1260
B19: INVESTIMENTO MENSAL
B20: Quanto investir por mês? | D20: 1260
B21: Por quantos anos? | D21: 5
B22: Taxa de rendimento mensal? | D22: 0.01079
B23: Patrimonio acumulado? | D23: {=FV(taxa_mensal,qtd_anos*12,aporte*-1)} -> 105558.91
B24: Dividendos mensais? | D24: {=patrimonio*rendimento_carteira} -> 950.0302
B26: CENÁRIOS | D26: DIVIDENDOS
A27: 2 | B27: Quanto em 2 anos? | C27: =FV($D$22,$A27*12,$D$20*-1) -> 34306.81 | D27: {=C27*rendimento_carteira} -> 308.76129
A28: 5 | B28: Quanto em 5 anos? | C28: =FV($D$22,$A28*12,$D$20*-1) -> 105558.91 | D28: {=C28*rendimento_carteira} -> 950.0302
A29: 10 | B29: Quanto em 10 anos? | C29: =FV($D$22,$A29*12,$D$20*-1) -> 306538.11 | D29: {=C29*rendimento_carteira} -> 2758.843
A30: 20 | B30: Quanto em 20 anos? | C30: =FV($D$22,$A30*12,$D$20*-1) -> 1417750 | D30: {=C30*rendimento_carteira} -> 12759.75
A31: 30 | B31: Quanto em 30 anos? | C31: =FV($D$22,$A31*12,$D$20*-1) -> 5445933.8 | D31: {=C31*rendimento_carteira} -> 49013.404
B33: PERFIL | C33: Agressivo
B34: Valor a ser investido por mês | C34: {=aporte} -> 1260
B36: TIPO DE FII | C36: PERCENTUAL SUGERIDO | D36: VALORES
B37: Papel | C37: =VLOOKUP($C$33&"-"&B37,Planilha2!$B:$E,4,FALSE) -> 0.5 | D37: =C37*$C$34 -> 630
B38: Tijolo | C38: =VLOOKUP($C$33&"-"&B38,Planilha2!$B:$E,4,FALSE) -> 0.1 | D38: =C38*$C$34 -> 126
B39: Híbridos | C39: =VLOOKUP($C$33&"-"&B39,Planilha2!$B:$E,4,FALSE) -> 0.05 | D39: =C39*$C$34 -> 63
B40: FOF | C40: =VLOOKUP($C$33&"-"&B40,Planilha2!$B:$E,4,FALSE) -> 0.05 | D40: =C40*$C$34 -> 63
B41: Desenvolvimento | C41: =VLOOKUP($C$33&"-"&B41,Planilha2!$B:$E,4,FALSE) -> 0.2 | D41: =C41*$C$34 -> 252
B42: Hotelaria | C42: =VLOOKUP($C$33&"-"&B42,Planilha2!$B:$E,4,FALSE) -> 0.1 | D42: =C42*$C$34 -> 126
B43: TOTAL | D43: =SUM(D37:D42) -> 1260

Sheet Planilha2
B3: CHAVE | C3: PERFIL | D3: TIPO DE FII | E3: %
B4: =C4&"-"&D4 -> Conservador-Papel | C4: Conservador | D4: Papel | E4: 0.3
B5: =C5&"-"&D5 -> Conservador-Tijolo | C5: Conservador | D5: Tijolo | E5: 0.5
B6: =C6&"-"&D6 -> Conservador-Híbridos | C6: Conservador | D6: Híbridos | E6: 0.1
B7: =C7&"-"&D7 -> Conservador-FOF | C7: Conservador | D7: FOF | E7: 0.1
B8: =C8&"-"&D8 -> Conservador-Desenvolvimento | C8: Conservador | D8: Desenvolvimento | E8: 0
B9: =C9&"-"&D9 -> Conservador-Hotelaria | C9: Conservador | D9: Hotelaria | E9: 0
B10: =C10&"-"&D10 -> Moderado-Papel | C10: Moderado | D10: Papel | E10: 0.32
B11: =C11&"-"&D11 -> Moderado-Tijolo | C11: Moderado | D11: Tijolo | E11: 0.35
B12: =C12&"-"&D12 -> Moderado-Híbridos | C12: Moderado | D12: Híbridos | E12: 0.08
B13: =C13&"-"&D13 -> Moderado-FOF | C13: Moderado | D13: FOF | E13: 0.05
B14: =C14&"-"&D14 -> Moderado-Desenvolvimento | C14: Moderado | D14: Desenvolvimento | E14: 0.1
B15: =C15&"-"&D15 -> Moderado-Hotelaria | C15: Moderado | D15: Hotelaria | E15: 0.1
... B21: =C21&"-"&D21 -> Agressivo-Hotelaria | C21: Agressivo | D21: Hotelaria | E21: 0.1
